core/__init__.py
core/ai.py
core/analytics.py
core/config.py
core/functions.py
core/main.py
core/tests/__init__.py
core/tests/test_truncate_text.py
gpt_code_search-0.0.9.dist-info/LICENSE
gpt_code_search-0.0.9.dist-info/METADATA
gpt_code_search-0.0.9.dist-info/WHEEL
gpt_code_search-0.0.9.dist-info/entry_points.txt
gpt_code_search-0.0.9.dist-info/RECORD
